searchcode/__init__.py
searchcode/_cli/__init__.py
searchcode/_cli/app.py
searchcode/_cli/panels.py
searchcode/_lib.py
searchcode/api.py
searchcode/filters.py
searchcode-0.6.4.dist-info/METADATA
searchcode-0.6.4.dist-info/WHEEL
searchcode-0.6.4.dist-info/entry_points.txt
searchcode-0.6.4.dist-info/licenses/LICENSE
searchcode-0.6.4.dist-info/RECORD
