Metadata-Version: 2.4
Name: searchcode
Version: 0.6.4
Summary: Simple, comprehensive code search
License: GPLv3+
License-File: LICENSE
Author: Ritchie Mwewa
Author-email: rly0nheart@duck.com
Requires-Python: >=3.10,<4.0
Classifier: Development Status :: 5 - Production/Stable
Classifier: Intended Audience :: Developers
Classifier: License :: OSI Approved :: GNU General Public License v3 or later (GPLv3+)
Classifier: License :: Other/Proprietary License
Classifier: Natural Language :: English
Classifier: Operating System :: OS Independent
Classifier: Programming Language :: Python :: 3
Classifier: Programming Language :: Python :: 3.10
Classifier: Programming Language :: Python :: 3.11
Classifier: Programming Language :: Python :: 3.12
Classifier: Programming Language :: Python :: 3.13
Classifier: Programming Language :: Python :: 3.14
Requires-Dist: requests (>=2.32.2,<3.0.0)
Requires-Dist: rich-click (>=1.8.9,<2.0.0)
Project-URL: Homepage, https://searchcode.com
Project-URL: Repository, https://codeberg.org/rly0nheart/searchcode-python
